<?xml version="1.0"?>
<!--
  ~ RHQ Management Platform
  ~ Copyright (C) 2005-2014 Red Hat, Inc.
  ~ All rights reserved.
  ~
  ~ This program is free software; you can redistribute it and/or modify
  ~ it under the terms of the GNU General Public License as published by
  ~ the Free Software Foundation version 2 of the License.
  ~
  ~ This program is distributed in the hope that it will be useful,
  ~ but WITHOUT ANY WARRANTY; without even the implied warranty of
  ~ MERCHANTABILITY or FITNESS FOR A PARTICULAR PURPOSE. See the
  ~ GNU General Public License for more details.
  ~
  ~ You should have received a copy of the GNU General Public License
  ~ along with this program; if not, write to the Free Software Foundation, Inc.,
  ~ 51 Franklin Street, Fifth Floor, Boston, MA 02110-1301, USA
  -->

<differences>
  <difference>
    <className>org/rhq/core/domain/resource/DeleteResourceHistory</className>
    <differenceType>6011</differenceType> <!-- constant removed -->
    <field>QUERY_DELETE_BY_RESOURCES</field>
    <justification>BZ 1168890</justification>
  </difference>
  <difference>
    <className>org/rhq/core/domain/resource/DeleteResourceHistory</className>
    <differenceType>7002</differenceType> <!-- method removed -->
    <method>org.rhq.core.domain.resource.Resource getResource()</method>
    <justification>BZ 1168890</justification>
  </difference>
  <difference>
    <className>org/rhq/core/domain/resource/DeleteResourceHistory</className>
    <differenceType>7002</differenceType> <!-- method removed -->
    <method>void setResource(org.rhq.core.domain.resource.Resource)</method>
    <justification>BZ 1168890</justification>
  </difference>
  <difference>
    <className>org/rhq/core/domain/resource/Resource</className>
    <differenceType>7002</differenceType> <!-- method removed -->
    <method>void addDeleteResourceHistory(org.rhq.core.domain.resource.DeleteResourceHistory)</method>
    <justification>BZ 1168890</justification>
  </difference>
  <difference>
    <className>org/rhq/core/domain/resource/Resource</className>
    <differenceType>7002</differenceType> <!-- method removed -->
    <method>java.util.List getDeleteResourceRequests()</method>
    <justification>BZ 1168890</justification>
  </difference>
  <difference>
    <className>org/rhq/core/domain/resource/Resource</className>
    <differenceType>7002</differenceType> <!-- method removed -->
    <method>void setDeleteResourceRequests(java.util.List)</method>
    <justification>BZ 1168890</justification>
  </difference>
    <difference>
    <className>org/rhq/core/domain/operation/composite/GroupOperationScheduleComposite</className>
    <differenceType>7004</differenceType><!-- number of args changed -->
    <method>GroupOperationScheduleComposite(int, java.lang.String, java.lang.String, java.lang.String, long, int, java.lang.String, java.lang.String)</method>
    <justification>Added autoGroupParentResourceId parameter - Bug 1202760</justification>
  </difference>

  
</differences>

